[
	{
		"imgFile": "IMG_20140129_lee_roz_1.jpg",
		"metadata": "lee, roz",
		"tags": [ "lee", "roz" ]
	},
	{
		"imgFile": "IMG_20140129_lee_roz_2.jpg",
		"metadata": "lee, roz",
		"tags": [ "lee", "roz" ]
	},
	{
		"imgFile": "IMG_20140129_roz_2.jpg",
		"metadata": "roz",
		"tags": [ "roz" ]
	},
	{
		"imgFile": "IMG_20140129_roz.jpg",
		"metadata": "roz",
		"tags": [ "roz" ]
	},
	{
		"imgFile": "IMG_20140201_ian_on_the_beach.jpg",
		"metadata": "ian, on, the, beach",
		"tags": [ "ian", "beach" ]
	},
	{
		"imgFile": "IMG_20140201_ian_patty_on_the_beach.jpg",
		"metadata": "ian, patty, on, the, beach",
		"tags": [ "ian", "patty", "beach" ]
	},
	{
		"imgFile": "IMG_20140201_ian_roz_lee_patty.jpg",
		"metadata": "ian, roz, lee, patty",
		"tags": [ "ian", "roz", "lee", "patty" ]
	},
	{
		"imgFile": "IMG_20140201_ian_steve_lee_patty_roz_restaurant_2.jpg",
		"metadata": "ian, steve, lee, patty, roz, restaurant (mom's birthday)",
		"tags": [ "ian", "steve", "lee", "patty", "roz", "restaurant", "birthday" ]
	},
	{
		"imgFile": "IMG_20140201_ian_steve_lee_patty_roz_restaurant.jpg",
		"metadata": "ian, steve, lee, patty, roz, vrestaurant (mom's birthday)",
		"tags": [ "ian", "steve", "lee", "patty", "roz", "restaurant", "birthday" ]
	},
	{
		"imgFile": "IMG_20140201_lee_ian_roz_restaurant.jpg",
		"metadata": "lee, ian, roz, restaurant (mom's birthday)",
		"tags": [ "lee", "ian", "roz", "restaurant", "birthday" ]
	},
	{
		"imgFile": "IMG_20140201_lee_roz_restaurant_2.jpg",
		"metadata": "lee, roz, restaurant (mom's birthday)",
		"tags": [ "lee", "roz", "restaurant", "birthday" ]
	},
	{
		"imgFile": "IMG_20140201_lee_roz_restaurant_3.jpg",
		"metadata": "lee, roz, restaurant (mom's birthday)",
		"tags": [ "lee", "roz", "restaurant", "birthday" ]
	},
	{
		"imgFile": "IMG_20140201_lee_roz_restaurant_4.jpg",
		"metadata": "lee, roz, restaurant (mom's birthday)",
		"tags": [ "lee", "roz", "restaurant", "birthday" ]
	},
	{
		"imgFile": "IMG_20140201_lee_roz_restaurant.jpg",
		"metadata": "lee, roz, restaurant (mom's birthday)",
		"tags": [ "lee", "roz", "restaurant", "birthday" ]
	},
	{
		"imgFile": "IMG_20140201_roz_ian_restaurant_3.jpg",
		"metadata": "roz, ian, restaurant (mom's birthday)",
		"tags": [ "roz", "ian", "restaurant", "birthday" ]
	},
	{
		"imgFile": "IMG_20140201_roz_ian_restaurant_4.jpg",
		"metadata": "roz, ian, restaurant (mom's birthday)",
		"tags": [ "roz", "ian", "restaurant", "birthday" ]
	},
	{
		"imgFile": "IMG_20140201_roz_ian_restaurant.jpg",
		"metadata": "roz, ian, restaurant (mom's birthday)",
		"tags": [ "roz", "ian", "restaurant", "birthday" ]
	},
	{
		"imgFile": "IMG_20140201_steve_ian_lee_patty_roz_restaurant_2.jpg",
		"metadata": "steve, ian, lee, patty, roz, restaurant (mom's birthday)",
		"tags": [ "steve", "ian", "lee", "patty", "roz", "restaurant", "birthday" ]
	},
	{
		"imgFile": "IMG_20140201_steve_ian_restaurant.jpg",
		"metadata": "steve, ian, restaurant (mom's birthday)",
		"tags": [ "steve", "ian", "restaurant", "birthday" ]
	},
	{
		"imgFile": "IMG_20140201_steve_on_the_beach_1.jpg",
		"metadata": "steve, on, the, beach",
		"tags": [ "steve", "beach" ]
	},
	{
		"imgFile": "IMG_20140201_steve_on_the_beach_2.jpg",
		"metadata": "steve, on, the, beach",
		"tags": [ "steve", "beach" ]
	},
	{
		"imgFile": "IMG_20140202_ian_kitchen_1.jpg",
		"metadata": "ian, kitchen",
		"tags": [ "ian", "kitchen" ]
	},
	{
		"imgFile": "IMG_20140202_ian_kitchen_2.jpg",
		"metadata": "ian, kitchen",
		"tags": [ "ian", "kitchen" ]
	},
	{
		"imgFile": "IMG_20140202_ian_kitchen_3.jpg",
		"metadata": "ian, kitchen",
		"tags": [ "ian", "kitchen" ]
	},
	{
		"imgFile": "IMG_20140202_steve_ian_lee.jpg",
		"metadata": "steve, ian, lee",
		"tags": [ "steve", "ian", "lee" ]
	}
]